CHANGELOG.txt
MANIFEST.in
README.md
classifiers_list.txt
instructions.txt
setup.py
pypi_hellodemo/__init__.py
pypi_hellodemo/helloname.py
pypi_hellodemo.egg-info/PKG-INFO
pypi_hellodemo.egg-info/SOURCES.txt
pypi_hellodemo.egg-info/dependency_links.txt
pypi_hellodemo.egg-info/top_level.txt