Metadata-Version: 1.0
Name: pypi-hellodemo
Version: 0.0.1
Summary: greeting package
Home-page: UNKNOWN
Author: Jesse DeSimone, Ph.D.
Author-email: desimone.neuro@gmail.com
License: UNKNOWN
Keywords: greeting
Platform: UNKNOWN
